fnvhash_c-0.1.4.data/purelib/fnvhash_c/__init__.py
fnvhash_c-0.1.4.data/purelib/fnvhash_c/bfilt.py
fnvhash_c-0.1.4.data/purelib/fnvhash_c/cityhash.cp37-win_amd64.pyd
fnvhash_c-0.1.4.data/purelib/fnvhash_c/fnvlib.cp37-win_amd64.pyd
fnvhash_c-0.1.4.dist-info/METADATA
fnvhash_c-0.1.4.dist-info/WHEEL
fnvhash_c-0.1.4.dist-info/top_level.txt
fnvhash_c-0.1.4.dist-info/RECORD
