Metadata-Version: 2.1
Name: fnvhash-c
Version: 0.1.4
Summary: Python FNV hash implementation based on cython, to give you an alternative high speed choice. - GoodManWEN/py-fnvhash-c
Home-page: https://github.com/GoodManWEN/py-fnvhash-c
Author: WEN
License: UNKNOWN
Project-URL: Bug Tracker, https://github.com/GoodManWEN/py-fnvhash-c/issues
Keywords: fnvhash-c,fnvhash,hash,fnv
Platform: UNKNOWN
Classifier: Programming Language :: Python :: 3
Classifier: Programming Language :: Python :: 3.6
Classifier: Programming Language :: Python :: 3.7
Classifier: Programming Language :: Python :: 3.8
Classifier: Programming Language :: Python :: 3.9
Classifier: Programming Language :: Python :: 3 :: Only
Classifier: License :: OSI Approved :: MIT License
Classifier: Operating System :: POSIX :: Linux
Classifier: Operating System :: Microsoft :: Windows
Requires-Python: >=3.6
